constants.py
tracker/__init__.py
tracker/__main__.py
tracker/ip_tracker.py
ip_locator-0.1.1.dist-info/METADATA
ip_locator-0.1.1.dist-info/WHEEL
ip_locator-0.1.1.dist-info/entry_points.txt
ip_locator-0.1.1.dist-info/licenses/LICENSE
ip_locator-0.1.1.dist-info/RECORD
