Metadata-Version: 2.4
Name: ip-locator
Version: 0.1.1
Summary: IP address geolocation and network information tool
Project-URL: Homepage, https://github.com/jmeiracorbal/ip-locator
Project-URL: Repository, https://github.com/jmeiracorbal/ip-locator
Project-URL: Issues, https://github.com/jmeiracorbal/ip-locator/issues
Author: jmeiracorbal
License: MIT License
License-File: LICENSE
Keywords: geolocation,ip,isp,lookup,network,osint
Classifier: Development Status :: 4 - Beta
Classifier: Intended Audience :: Developers
Classifier: License :: OSI Approved :: MIT License
Classifier: Programming Language :: Python :: 3
Classifier: Programming Language :: Python :: 3.8
Classifier: Programming Language :: Python :: 3.9
Classifier: Programming Language :: Python :: 3.10
Classifier: Programming Language :: Python :: 3.11
Classifier: Programming Language :: Python :: 3.12
Classifier: Programming Language :: Python :: 3.13
Classifier: Topic :: Software Development :: Libraries :: Python Modules
Classifier: Topic :: Utilities
Requires-Python: <3.14,>=3.8
Requires-Dist: requests>=2.31.0
Provides-Extra: dev
Requires-Dist: pyinstaller>=6.15.0; extra == 'dev'
